README.md
setup.py
django_access_log/__init__.py
django_access_log/formatters.py
django_access_log/handlers.py
django_access_log/middleware.py
django_access_log.egg-info/PKG-INFO
django_access_log.egg-info/SOURCES.txt
django_access_log.egg-info/dependency_links.txt
django_access_log.egg-info/top_level.txt