Metadata-Version: 1.0
Name: django-access-log
Version: 1.1.1
Summary: django access log
Home-page: https://github.com/linchaonan2010/django-access-log
Author: linchaonan
Author-email: 1952593993@qq.com
License: BSD
Platform: UNKNOWN
